COPYING
MANIFEST.in
README.rst
bootstrap-buildout.py
buildout.cfg
develop.cfg
requirements.txt
setup.py
version.txt
bob/__init__.py
bob.bio.pericrosseye_competition.egg-info/PKG-INFO
bob.bio.pericrosseye_competition.egg-info/SOURCES.txt
bob.bio.pericrosseye_competition.egg-info/dependency_links.txt
bob.bio.pericrosseye_competition.egg-info/entry_points.txt
bob.bio.pericrosseye_competition.egg-info/not-zip-safe
bob.bio.pericrosseye_competition.egg-info/requires.txt
bob.bio.pericrosseye_competition.egg-info/top_level.txt
bob/bio/__init__.py
bob/bio/pericrosseye_competition/__init__.py
bob/bio/pericrosseye_competition/competition/Authentication.py
bob/bio/pericrosseye_competition/competition/GrassmanGaborJet.py
bob/bio/pericrosseye_competition/competition/ISV.py
bob/bio/pericrosseye_competition/competition/__init__.py
bob/bio/pericrosseye_competition/extractor/__init__.py
bob/bio/pericrosseye_competition/extractor/eye_graph.py
bob/bio/pericrosseye_competition/preprocessor/__init__.py
bob/bio/pericrosseye_competition/preprocessor/geometric_norm_crop.py
bob/bio/pericrosseye_competition/preprocessor/raw_crop.py
bob/bio/pericrosseye_competition/script/__init__.py
bob/bio/pericrosseye_competition/script/evaluate_pericrosseye.py
bob/bio/pericrosseye_competition/script/generate_normalizer.py
bob/bio/pericrosseye_competition/script/perienroll_idiap.py
bob/bio/pericrosseye_competition/script/perienroll_idiap_gfk.py
bob/bio/pericrosseye_competition/script/perienroll_idiap_gfk_10d.py
bob/bio/pericrosseye_competition/script/perimatch_idiap.py
bob/bio/pericrosseye_competition/script/perimatch_idiap_gfk.py
bob/bio/pericrosseye_competition/script/perimatch_idiap_gfk_10d.py
bob/bio/pericrosseye_competition/script/show_periocular_jets.py
bob/bio/pericrosseye_competition/script/utils.py
bob/bio/pericrosseye_competition/test/__init__.py
bob/bio/pericrosseye_competition/test/test.py
bob/bio/pericrosseye_competition/test/data/background_gfk.hdf5
bob/bio/pericrosseye_competition/test/data/background_gfk_10d.hdf5
bob/bio/pericrosseye_competition/test/data/background_model.hdf5
bob/bio/pericrosseye_competition/test/data/periocular_model.bmp
bob/bio/pericrosseye_competition/test/data/periocular_probe.bmp
doc/conf.py
doc/index.rst
doc/installation.rst
doc/tunning.rst