Metadata-Version: 1.1
Name: bob.bio.pericrosseye-competition
Version: 1.0.1
Summary: This package contains the scripts to reproduce the experiments of the 2nd Cross-Spectrum Iris/Periocular Recognition competition
Home-page: https://gitlab.idiap.ch/bob/bob.bio.pericrosseye_competition
Author: Tiago de Freitas Pereira
Author-email: tiago.pereira@idiap.ch
License: BSD
Keywords: bob,biometric recognition,evaluation
Platform: UNKNOWN
Classifier: Framework :: Bob
Classifier: Development Status :: 3 - Alpha
Classifier: Intended Audience :: Developers
Classifier: License :: OSI Approved :: BSD License
Classifier: Natural Language :: English
Classifier: Programming Language :: Python
Classifier: Topic :: Scientific/Engineering :: Artificial Intelligence
